footnotes2/__init__.py
footnotes2/footnotes2.py
markdown_footnotes-0.1.1.dist-info/LICENSE
markdown_footnotes-0.1.1.dist-info/METADATA
markdown_footnotes-0.1.1.dist-info/WHEEL
markdown_footnotes-0.1.1.dist-info/top_level.txt
markdown_footnotes-0.1.1.dist-info/RECORD
