Metadata-Version: 2.1
Name: markdown-footnotes
Version: 0.1.1
Summary: The official Python-Markdown "footnotes" extension, with additional options.
Home-page: https://github.com/wilhelmer/markdown-footnotes.git
Author: Lars Wilhelmer
Author-email: lars@wilhelmer.de
License: MIT
Keywords: markdown footnotes
License-File: LICENSE
Requires-Dist: Markdown (>=3.0.1)
